fixfonts-1.0.1.dist-info/DESCRIPTION.rst
fixfonts-1.0.1.dist-info/metadata.json
fixfonts-1.0.1.dist-info/METADATA
fixfonts-1.0.1.dist-info/top_level.txt
fixfonts-1.0.1.dist-info/RECORD
fixfonts-1.0.1.dist-info/WHEEL
fixfonts-1.0.1.dist-info/entry_points.txt
fixfonts/__init__.py
fixfonts/app.py
