Metadata-Version: 2.0
Name: fixfonts
Version: 1.0.1
Summary: Removes width inconsistency in fonts, enabling their use in Windows tools like PuTTY
Home-page: https://github.com/scott-hand/fix-fixed-fonts
Author: Scott Hand
Author-email: scott@vkgfx.com
License: UNKNOWN
Platform: UNKNOWN
Classifier: Development Status :: 4 - Beta
Classifier: Intended Audience :: Developers
Classifier: Programming Language :: Python :: 2
